{
    "cuisines": [
        {
            "cuisine": {
                "cuisine_id": 1035,
                "cuisine_name": "Afghan"
            }
        },
        {
            "cuisine": {
                "cuisine_id": 6,
                "cuisine_name": "Afghani"
            }
        },
        {
            "cuisine": {
                "cuisine_id": 1,
                "cuisine_name": "American"
            }
        },
        {
            "cuisine": {
                "cuisine_id": 193,
                "cuisine_name": "BBQ"
            }
        },
        {
            "cuisine": {
                "cuisine_id": 5,
                "cuisine_name": "Bakery"
            }
        },
        {
            "cuisine": {
                "cuisine_id": 270,
                "cuisine_name": "Beverages"
            }
        },
        {
            "cuisine": {
                "cuisine_id": 7,
                "cuisine_name": "Biryani"
            }
        },
        {
            "cuisine": {
                "cuisine_id": 168,
                "cuisine_name": "Burger"
            }
        },
        {
            "cuisine": {
                "cuisine_id": 30,
                "cuisine_name": "Cafe"
            }
        },
        {
            "cuisine": {
                "cuisine_id": 1039,
                "cuisine_name": "Cafe Food"
            }
        },
        {
            "cuisine": {
                "cuisine_id": 25,
                "cuisine_name": "Chinese"
            }
        },
        {
            "cuisine": {
                "cuisine_id": 1040,
                "cuisine_name": "Coffee"
            }
        },
        {
            "cuisine": {
                "cuisine_id": 35,
                "cuisine_name": "Continental"
            }
        },
        {
            "cuisine": {
                "cuisine_id": 100,
                "cuisine_name": "Desserts"
            }
        },
        {
            "cuisine": {
                "cuisine_id": 38,
                "cuisine_name": "European"
            }
        },
        {
            "cuisine": {
                "cuisine_id": 40,
                "cuisine_name": "Fast Food"
            }
        },
        {
            "cuisine": {
                "cuisine_id": 271,
                "cuisine_name": "Finger Food"
            }
        },
        {
            "cuisine": {
                "cuisine_id": 1059,
                "cuisine_name": "Grocery"
            }
        },
        {
            "cuisine": {
                "cuisine_id": 143,
                "cuisine_name": "Healthy Food"
            }
        },
        {
            "cuisine": {
                "cuisine_id": 49,
                "cuisine_name": "Hyderabadi"
            }
        },
        {
            "cuisine": {
                "cuisine_id": 233,
                "cuisine_name": "Ice Cream"
            }
        },
        {
            "cuisine": {
                "cuisine_id": 148,
                "cuisine_name": "Indian"
            }
        },
        {
            "cuisine": {
                "cuisine_id": 55,
                "cuisine_name": "Italian"
            }
        },
        {
            "cuisine": {
                "cuisine_id": 164,
                "cuisine_name": "Juices"
            }
        },
        {
            "cuisine": {
                "cuisine_id": 178,
                "cuisine_name": "Kebab"
            }
        },
        {
            "cuisine": {
                "cuisine_id": 62,
                "cuisine_name": "Kerala"
            }
        },
        {
            "cuisine": {
                "cuisine_id": 73,
                "cuisine_name": "Mexican"
            }
        },
        {
            "cuisine": {
                "cuisine_id": 1015,
                "cuisine_name": "Mithai"
            }
        },
        {
            "cuisine": {
                "cuisine_id": 1051,
                "cuisine_name": "Momos"
            }
        },
        {
            "cuisine": {
                "cuisine_id": 75,
                "cuisine_name": "Mughlai"
            }
        },
        {
            "cuisine": {
                "cuisine_id": 50,
                "cuisine_name": "North Indian"
            }
        },
        {
            "cuisine": {
                "cuisine_id": 82,
                "cuisine_name": "Pizza"
            }
        },
        {
            "cuisine": {
                "cuisine_id": 88,
                "cuisine_name": "Rajasthani"
            }
        },
        {
            "cuisine": {
                "cuisine_id": 1005,
                "cuisine_name": "Roast Chicken"
            }
        },
        {
            "cuisine": {
                "cuisine_id": 1023,
                "cuisine_name": "Rolls"
            }
        },
        {
            "cuisine": {
                "cuisine_id": 998,
                "cuisine_name": "Salad"
            }
        },
        {
            "cuisine": {
                "cuisine_id": 304,
                "cuisine_name": "Sandwich"
            }
        },
        {
            "cuisine": {
                "cuisine_id": 83,
                "cuisine_name": "Seafood"
            }
        },
        {
            "cuisine": {
                "cuisine_id": 85,
                "cuisine_name": "South Indian"
            }
        },
        {
            "cuisine": {
                "cuisine_id": 90,
                "cuisine_name": "Street Food"
            }
        },
        {
            "cuisine": {
                "cuisine_id": 1024,
                "cuisine_name": "Wraps"
            }
        }
    ]
}
